scidx_streaming/__init__.py
scidx_streaming/client/__init__.py
scidx_streaming/client/filters.py
scidx_streaming/client/init_client.py
scidx_streaming/client/registration.py
scidx_streaming/client/search.py
scidx_streaming/client/streams.py
scidx_streaming/connectors/__init__.py
scidx_streaming/connectors/ckan/__init__.py
scidx_streaming/connectors/ckan/actions.py
scidx_streaming/connectors/ckan/client.py
scidx_streaming/connectors/ckan/payloads.py
scidx_streaming/connectors/kafka/__init__.py
scidx_streaming/connectors/kafka/cluster.py
scidx_streaming/connectors/kafka/connection.py
scidx_streaming/connectors/kafka/endpoint.py
scidx_streaming/data_cleaning/__init__.py
scidx_streaming/data_cleaning/filter_compiler.py
scidx_streaming/data_cleaning/filter_evaluator.py
scidx_streaming/data_cleaning/filter_runner.py
scidx_streaming/data_cleaning/filter_utils.py
scidx_streaming/data_cleaning/filters.py
scidx_streaming/resources/__init__.py
scidx_streaming/resources/delete.py
scidx_streaming/resources/register.py
scidx_streaming/resources/search.py
scidx_streaming/resources/update.py
scidx_streaming/resources/utils/__init__.py
scidx_streaming/resources/utils/common.py
scidx_streaming/resources/utils/dataset_recreate.py
scidx_streaming/resources/utils/dataset_snapshot.py
scidx_streaming/resources/utils/datasets.py
scidx_streaming/resources/utils/registry.py
scidx_streaming/resources/utils/types/__init__.py
scidx_streaming/resources/utils/types/api_stream.py
scidx_streaming/resources/utils/types/kafka.py
scidx_streaming/resources/utils/types/rss.py
scidx_streaming/resources/utils/types/static_file.py
scidx_streaming/streams/__init__.py
scidx_streaming/streams/builder.py
scidx_streaming/streams/consumer.py
scidx_streaming/streams/local.py
scidx_streaming/streams/creation/__init__.py
scidx_streaming/streams/creation/base.py
scidx_streaming/streams/creation/common.py
scidx_streaming/streams/creation/types/__init__.py
scidx_streaming/streams/creation/types/kafka.py
scidx_streaming-0.1.9.dist-info/licenses/AUTHORS
scidx_streaming-0.1.9.dist-info/licenses/LICENSE
scidx_streaming-0.1.9.dist-info/METADATA
scidx_streaming-0.1.9.dist-info/WHEEL
scidx_streaming-0.1.9.dist-info/top_level.txt
scidx_streaming-0.1.9.dist-info/RECORD
