Metadata-Version: 2.4
Name: scidx_streaming
Version: 0.1.9
Summary: A Python client library for interacting with the scidx POP and create streams.
Home-page: https://github.com/sci-ndp/streaming-py
Author: Andreu Fornos, Raul Bardaji, Saleem Alharir
Author-email: andreu.fornos@utah.edu, rbardaji@gmail.com, saleem.alharir@utah.edu
Classifier: Programming Language :: Python :: 3
Classifier: License :: OSI Approved :: MIT License
Classifier: Operating System :: OS Independent
Requires-Python: >=3.6
License-File: LICENSE
License-File: AUTHORS
Requires-Dist: absl-py>=1.4
Requires-Dist: ndp-ep>=0.3.0
Requires-Dist: kafka-python>=2.0.2
Requires-Dist: aiokafka>=0.8
Requires-Dist: pydantic<3,>=2.6
Requires-Dist: python-dotenv>=1.0
Requires-Dist: pandas>=1.5
Requires-Dist: pytest>=7.4
Requires-Dist: coverage>=7.4
Dynamic: author
Dynamic: author-email
Dynamic: classifier
Dynamic: description
Dynamic: description-content-type
Dynamic: home-page
Dynamic: license-file
Dynamic: requires-dist
Dynamic: requires-python
Dynamic: summary
